kitech_repository/__init__.py
kitech_repository/cli/__init__.py
kitech_repository/cli/main.py
kitech_repository/cli/utils.py
kitech_repository/cli/commands/__init__.py
kitech_repository/cli/commands/auth.py
kitech_repository/cli/commands/config.py
kitech_repository/cli/commands/download.py
kitech_repository/cli/commands/explore.py
kitech_repository/cli/commands/list_cmd.py
kitech_repository/cli/commands/login.py
kitech_repository/cli/commands/logout.py
kitech_repository/cli/commands/manager.py
kitech_repository/cli/commands/server.py
kitech_repository/cli/commands/start.py
kitech_repository/cli/commands/status.py
kitech_repository/cli/commands/upload.py
kitech_repository/core/__init__.py
kitech_repository/core/auth.py
kitech_repository/core/client.py
kitech_repository/core/config.py
kitech_repository/core/exceptions.py
kitech_repository/core/zip_utils.py
kitech_repository/models/__init__.py
kitech_repository/models/file.py
kitech_repository/models/repository.py
kitech_repository/models/response.py
kitech_repository/tui/__init__.py
kitech_repository/tui/app.py
kitech_repository/tui/messages.py
kitech_repository/tui/models.py
kitech_repository/tui/screens/__init__.py
kitech_repository/tui/screens/file_manager.py
kitech_repository/tui/screens/repository_selection.py
kitech_repository/tui/styles/__init__.py
kitech_repository/tui/styles/main.tcss
kitech_repository/tui/widgets/__init__.py
kitech_repository/tui/widgets/confirmation_dialog.py
kitech_repository/tui/widgets/local_panel.py
kitech_repository/tui/widgets/progress_panel.py
kitech_repository/tui/widgets/remote_panel.py
kitech_repository-0.1.16.dist-info/METADATA
kitech_repository-0.1.16.dist-info/WHEEL
kitech_repository-0.1.16.dist-info/entry_points.txt
kitech_repository-0.1.16.dist-info/RECORD
