Metadata-Version: 2.4
Name: kitech-repository
Version: 0.1.16
Summary: KITECH Manufacturing Data Repository CLI and Library
Project-URL: Homepage, https://github.com/kitech/kitech-repository
Project-URL: Documentation, https://github.com/kitech/kitech-repository#readme
Project-URL: Repository, https://github.com/kitech/kitech-repository.git
Project-URL: Issues, https://github.com/kitech/kitech-repository/issues
Author-email: KITECH <kitech@kitech.re.kr>
License-Expression: MIT
Keywords: cli,data,file-manager,kitech,manufacturing,repository,tui
Classifier: Development Status :: 4 - Beta
Classifier: Environment :: Console
Classifier: Intended Audience :: Developers
Classifier: Intended Audience :: Manufacturing
Classifier: Intended Audience :: Science/Research
Classifier: License :: OSI Approved :: MIT License
Classifier: Operating System :: OS Independent
Classifier: Programming Language :: Python :: 3
Classifier: Programming Language :: Python :: 3.10
Classifier: Programming Language :: Python :: 3.11
Classifier: Programming Language :: Python :: 3.12
Classifier: Programming Language :: Python :: 3.13
Classifier: Topic :: Scientific/Engineering
Classifier: Topic :: System :: Archiving
Classifier: Topic :: System :: Systems Administration
Classifier: Topic :: Utilities
Requires-Python: <3.14,>=3.10
Requires-Dist: aiofiles>=23.2.1
Requires-Dist: click>=8.1.0
Requires-Dist: httpx>=0.25.0
Requires-Dist: keyring>=24.0.0
Requires-Dist: pydantic>=2.5.0
Requires-Dist: python-dotenv>=1.0.0
Requires-Dist: rich>=13.7.0
Requires-Dist: textual>=0.47.0
Requires-Dist: tqdm>=4.66.0
Requires-Dist: typer>=0.9.0
Provides-Extra: alt-keyring
Requires-Dist: keyrings-alt>=5.0.0; extra == 'alt-keyring'
Provides-Extra: dev
Requires-Dist: pytest-asyncio>=0.21.0; extra == 'dev'
Requires-Dist: pytest-cov>=4.1.0; extra == 'dev'
Requires-Dist: pytest-httpx>=0.30.0; extra == 'dev'
Requires-Dist: pytest-mock>=3.11.0; extra == 'dev'
Requires-Dist: pytest>=7.4.0; extra == 'dev'
Requires-Dist: ruff>=0.1.0; extra == 'dev'
Requires-Dist: textual-dev>=1.0.0; extra == 'dev'
